busyboulder/__init__.py
busyboulder/cli.py
busyboulder/data/__init__.py
busyboulder/data/gym_data.yaml
busyboulder-0.0.7.dist-info/LICENSE.txt
busyboulder-0.0.7.dist-info/METADATA
busyboulder-0.0.7.dist-info/WHEEL
busyboulder-0.0.7.dist-info/entry_points.txt
busyboulder-0.0.7.dist-info/top_level.txt
busyboulder-0.0.7.dist-info/RECORD
